Metadata-Version: 1.0
Name: om-transliterator
Version: 0.1.dev0
Summary: Kannada to Latin ISO 15919 (Romanisation) Transliterator.
Home-page: https://github.com/shrirambhat/om_transliterator
Author: Shriram Bhat
Author-email: mail@shrirambhat.com
License: LICENSE.txt
Keywords: kannada english latin romanization iso15919 transliteration tool
Platform: UNKNOWN
